graceful/__init__.py
graceful/authentication.py
graceful/authorization.py
graceful/errors.py
graceful/fields.py
graceful/parameters.py
graceful/serializers.py
graceful/validators.py
graceful/__pycache__/__init__.cpython-33.pyc
graceful/__pycache__/__init__.cpython-34.pyc
graceful/__pycache__/errors.cpython-33.pyc
graceful/__pycache__/errors.cpython-34.pyc
graceful/__pycache__/fields.cpython-33.pyc
graceful/__pycache__/fields.cpython-34.pyc
graceful/__pycache__/parameters.cpython-33.pyc
graceful/__pycache__/parameters.cpython-34.pyc
graceful/__pycache__/serializers.cpython-33.pyc
graceful/__pycache__/serializers.cpython-34.pyc
graceful/__pycache__/validators.cpython-33.pyc
graceful/__pycache__/validators.cpython-34.pyc
graceful/extras/__init__.py
graceful/extras/__pycache__/__init__.cpython-33.pyc
graceful/extras/__pycache__/__init__.cpython-34.pyc
graceful/resources/__init__.py
graceful/resources/base.py
graceful/resources/generic.py
graceful/resources/mixins.py
graceful-0.6.3.dist-info/METADATA
graceful-0.6.3.dist-info/RECORD
graceful-0.6.3.dist-info/WHEEL
graceful-0.6.3.dist-info/top_level.txt
graceful-0.6.3.dist-info/zip-safe
