Metadata-Version: 2.1
Name: graceful
Version: 0.6.3
Summary: Elegant Python REST toolkit built on top of falcon
Home-page: https://github.com/swistakm/graceful
Author: Michał Jaworski
Author-email: swistakm@gmail.com
License: BSD
Platform: UNKNOWN
Classifier: Development Status :: 5 - Production/Stable
Classifier: Intended Audience :: Developers
Classifier: License :: OSI Approved :: BSD License
Classifier: Operating System :: OS Independent
Classifier: Topic :: Software Development :: Libraries :: Application Frameworks
Classifier: Programming Language :: Python
Classifier: Programming Language :: Python :: 3.3
Classifier: Programming Language :: Python :: 3.4
Classifier: Programming Language :: Python :: 3.5
Classifier: Programming Language :: Python :: 3.6
Classifier: Programming Language :: Python :: 3 :: Only
Classifier: Topic :: Internet :: WWW/HTTP :: WSGI
Requires-Dist: falcon
Requires-Dist: singledispatch
